dlcu/__init__.py
dlcu/plot.py
dlcu/time_in_each_roi.py
dlcu/version.py
dlcu-0.0.5.dist-info/WHEEL
dlcu-0.0.5.dist-info/METADATA
dlcu-0.0.5.dist-info/RECORD
