Metadata-Version: 2.1
Name: dlcu
Version: 0.0.5
Summary: This package contains material from the DeepLabCut-Utils repository by DeepLabCut.
Home-page: https://github.com/bchaselab/dlcu
License: UNKNOWN
Author: fcatus
Author-email: f.catus@pm.me
